lion_service/__init__.py
lion_service/complete_request_info.py
lion_service/imodel.py
lion_service/rate_limiter.py
lion_service/service.py
lion_service/service_match_util.py
lion_service/service_util.py
lion_service/token_calculator.py
lion_service/version.py
lion_service-1.2.0.dist-info/LICENSE
lion_service-1.2.0.dist-info/METADATA
lion_service-1.2.0.dist-info/WHEEL
lion_service-1.2.0.dist-info/top_level.txt
lion_service-1.2.0.dist-info/RECORD
