Metadata-Version: 2.1
Name: lion-service
Version: 1.2.0
Summary: lion api service system
Author-email: HaiyangLi <quantocean.li@gmail.com>, Alina Luo <lluo25@fordham.edu>
License:            Apache License
Classifier: Programming Language :: Python :: 3
Classifier: Programming Language :: Python :: 3 :: Only
Classifier: Programming Language :: Python :: 3.11
Classifier: Programming Language :: Python :: 3.12
Classifier: Programming Language :: Python :: 3.13
Classifier: Intended Audience :: Developers
Classifier: License :: OSI Approved :: Apache Software License
Classifier: Operating System :: OS Independent
Classifier: Framework :: Pydantic
Classifier: Framework :: Pydantic :: 2
Classifier: Framework :: Pytest
Requires-Python: >=3.11
License-File: LICENSE
Requires-Dist: aiocache>=0.12.3
Requires-Dist: aiohttp>=3.11.10
Requires-Dist: pydantic>=2.10.3
Requires-Dist: tiktoken>=0.8.0
